ward_coverage/__init__.py
ward_coverage/hook_impl.py
ward_coverage-0.3.1.dist-info/LICENSE
ward_coverage-0.3.1.dist-info/METADATA
ward_coverage-0.3.1.dist-info/WHEEL
ward_coverage-0.3.1.dist-info/RECORD
