Metadata-Version: 2.1
Name: ward_coverage
Version: 0.3.1
Summary: A coverage plugin for Ward testing framework
Home-page: https://github.com/petereon/ward_coverage
License: MIT
Keywords: python
Author: Peter Vyboch
Author-email: pvyboch1@gmail.com
Requires-Python: >=3.7.8,<4.0.0
Classifier: License :: OSI Approved :: MIT License
Classifier: Programming Language :: Python :: 3
Classifier: Programming Language :: Python :: 3.8
Classifier: Programming Language :: Python :: 3.9
Classifier: Programming Language :: Python :: 3.10
Classifier: Programming Language :: Python :: 3.11
Classifier: Programming Language :: Python :: 3.12
Requires-Dist: coverage (>=5.0)
Requires-Dist: cucumber-tag-expressions (>3)
Requires-Dist: ward
Project-URL: Repository, https://github.com/petereon/ward_coverage
